{
  "persona": {
    "Isabella Rodriguez": {
      "movement": [
        78,
        19
      ],
      "pronunciatio": "\ud83d\udcbc",
      "description": "working at the counter at Hobbs Cafe @ the Ville:Hobbs Cafe:cafe:behind the cafe counter",
      "chat": null
    },
    "Maria Lopez": {
      "movement": [
        62,
        38
      ],
      "pronunciatio": "\ud83d\udce6",
      "description": "finishing up administrative tasks and closing the store for the day (placing orders for any low or out of stock items) @ the Ville:The Willows Market and Pharmacy:store:grocery store counter",
      "chat": null
    },
    "Klaus Mueller": {
      "movement": [
        61,
        37
      ],
      "pronunciatio": "\ud83d\udeb6",
      "description": "organizing activities and overseeing maintenance at the park (taking a quick walk around the park to make sure everything is in order) @ the Ville:Johnson Park:park:park garden",
      "chat": null
    }
  },
  "meta": {
    "curr_time": "February 14, 2023, 17:18:10"
  }
}