{
  "persona": {
    "Isabella Rodriguez": {
      "movement": [
        73,
        19
      ],
      "pronunciatio": "\ud83d\udce6",
      "description": "opening Hobbs Cafe and working at the counter (checking the inventory and restocking if needed) @ the Ville:Hobbs Cafe:cafe:refrigerator",
      "chat": null
    },
    "Maria Lopez": {
      "movement": [
        123,
        57
      ],
      "pronunciatio": "\ud83d\udecf\ufe0f",
      "description": "waking up and completing their morning routine (making their bed) @ the Ville:Dorm for Oak Hill College:Maria Lopez's room:bed",
      "chat": null
    },
    "Klaus Mueller": {
      "movement": [
        123,
        46
      ],
      "pronunciatio": "\ud83c\udf73",
      "description": "having breakfast (preparing breakfast) @ the Ville:Dorm for Oak Hill College:kitchen:cooking area",
      "chat": null
    }
  },
  "meta": {
    "curr_time": "February 15, 2023, 08:18:30"
  }
}