{
  "persona": {
    "Isabella Rodriguez": {
      "movement": [
        79,
        25
      ],
      "pronunciatio": "\ud83d\udd12",
      "description": "getting ready for bed and reflecting on the fun night with friends (turning off all the lights and locking up Hobbs Cafe) @ the Ville:Hobbs Cafe:cafe:cafe customer seating",
      "chat": null
    },
    "Maria Lopez": {
      "movement": [
        124,
        53
      ],
      "pronunciatio": "\ud83d\udec1\ud83d\udca4",
      "description": "reading before going to sleep (getting ready for bed) @ the Ville:Dorm for Oak Hill College:Maria Lopez's room:bed",
      "chat": null
    },
    "Klaus Mueller": {
      "movement": [
        72,
        23
      ],
      "pronunciatio": "\ud83d\udcdd",
      "description": "co-planning tomorrow's friends night out with Isabella and Maria at Hobbs Cafe (on the way to meeting with Isabella and Maria at Hobbs Cafe) (reviewing the event details and itinerary) @ the Ville:Hobbs Cafe:cafe:cafe customer seating",
      "chat": null
    }
  },
  "meta": {
    "curr_time": "February 14, 2023, 23:18:30"
  }
}