{
  "persona": {
    "Isabella Rodriguez": {
      "movement": [
        72,
        19
      ],
      "pronunciatio": "\u2615",
      "description": "enjoying a cup of coffee and chatting with her friends at the cafe (preparing the coffee for herself and her friends) @ the Ville:Hobbs Cafe:cafe:refrigerator",
      "chat": null
    },
    "Maria Lopez": {
      "movement": [
        123,
        48
      ],
      "pronunciatio": "\ud83c\udf45",
      "description": "having dinner at home (preparing ingredients for dinner) @ the Ville:Dorm for Oak Hill College:kitchen:cooking area",
      "chat": null
    },
    "Klaus Mueller": {
      "movement": [
        82,
        21
      ],
      "pronunciatio": "\ud83d\udde3\ufe0f",
      "description": "co-planning the friends night out at Hobbs Cafe with Isabella and Maria (discussing potential activities for the night) @ the Ville:Hobbs Cafe:cafe:cafe customer seating",
      "chat": null
    }
  },
  "meta": {
    "curr_time": "February 14, 2023, 21:04:40"
  }
}