{
  "persona": {
    "Isabella Rodriguez": {
      "movement": [
        76,
        19
      ],
      "pronunciatio": "\ud83d\udcbb",
      "description": "working at the counter @ the Ville:Hobbs Cafe:cafe:cooking area",
      "chat": null
    },
    "Maria Lopez": {
      "movement": [
        119,
        47
      ],
      "pronunciatio": "\ud83d\udcda",
      "description": "reviewing and updating employee training materials @ the Ville:Dorm for Oak Hill College:common room:common room table",
      "chat": null
    },
    "Klaus Mueller": {
      "movement": [
        27,
        44
      ],
      "pronunciatio": "\ud83d\udd7a",
      "description": "participating in outdoor activities with Isabella and Maria (demonstrating the first activity) @ the Ville:Johnson Park:park:park garden",
      "chat": null
    }
  },
  "meta": {
    "curr_time": "February 14, 2023, 19:32:20"
  }
}