{
  "persona": {
    "Isabella Rodriguez": {
      "movement": [
        75,
        51
      ],
      "pronunciatio": "\ud83c\udfa5",
      "description": "going to a movie with Maria and Klaus (checking the movie showtimes) @ the Ville:The Willows Market and Pharmacy:store:behind the pharmacy counter",
      "chat": null
    },
    "Maria Lopez": {
      "movement": [
        68,
        46
      ],
      "pronunciatio": "\ud83d\udeb6\u200d\u2642",
      "description": "working at the supply store (on the way to working at the supply stor) @ the Ville:Harvey Oak Supply Store:supply store:supply store counter",
      "chat": null
    },
    "Klaus Mueller": {
      "movement": [
        127,
        46
      ],
      "pronunciatio": "\ud83d\ude34",
      "description": "going to bed @ the Ville:Dorm for Oak Hill College:Klaus Mueller's room:bed",
      "chat": null
    }
  },
  "meta": {
    "curr_time": "February 14, 2023, 22:49:40"
  }
}